LICENSE
entrainment_metrics/__init__.py
entrainment_metrics/continuous/__init__.py
entrainment_metrics/continuous/continuous_time_series.py
entrainment_metrics/continuous/metrics.py
entrainment_metrics/continuous/utils.py
entrainment_metrics/extractStandardAcoustics.praat
entrainment_metrics/interpausal_unit.py
entrainment_metrics/tama/__init__.py
entrainment_metrics/tama/entrainment.py
entrainment_metrics/tama/frame.py
entrainment_metrics/tama/utils.py
entrainment_metrics/utils.py
entrainment_metrics-1.0.6.dist-info/LICENSE
entrainment_metrics-1.0.6.dist-info/METADATA
entrainment_metrics-1.0.6.dist-info/WHEEL
entrainment_metrics-1.0.6.dist-info/RECORD
