Metadata-Version: 2.1
Name: entrainment-metrics
Version: 1.0.6
Summary: Measure acoustic-prosodic entrainment in speech
Home-page: https://github.com/erikernst4/entrainment-metrics
License: Apache-2.0
Keywords: speech,prosody,speech-analysis,entrainment,prosodic-analysis
Author: E. Ernst, A. Gravano, R. Gálvez
Requires-Python: >=3.8,<3.11
Classifier: License :: OSI Approved :: Apache Software License
Classifier: Programming Language :: Python :: 3
Classifier: Programming Language :: Python :: 3.8
Classifier: Programming Language :: Python :: 3.9
Classifier: Programming Language :: Python :: 3.10
Requires-Dist: allosaurus (>=1.0.2,<2.0.0)
Requires-Dist: click (==8.0.2)
Requires-Dist: coverage (>=6.4.4,<7.0.0)
Requires-Dist: matplotlib (>=3.6.3,<4.0.0)
Requires-Dist: opensmile (>=2.4.1,<3.0.0)
Requires-Dist: praat-parselmouth (>=0.4.3,<0.5.0)
Requires-Dist: scikit-learn (>=1.3.2,<2.0.0)
Requires-Dist: scipy (>=1.8.1,<2.0.0)
Project-URL: Documentation, https://entrainment-metrics.readthedocs.io/en/latest/
Project-URL: Repository, https://github.com/erikernst4/entrainment-metrics
